uModbus_extended-1.0.4.dist-info/METADATA
uModbus_extended-1.0.4.dist-info/RECORD
uModbus_extended-1.0.4.dist-info/WHEEL
uModbus_extended-1.0.4.dist-info/top_level.txt
umodbus/__init__.py
umodbus/config.py
umodbus/exceptions.py
umodbus/functions.py
umodbus/route.py
umodbus/utils.py
umodbus/client/__init__.py
umodbus/client/tcp.py
umodbus/client/serial/__init__.py
umodbus/client/serial/redundancy_check.py
umodbus/client/serial/rtu.py
umodbus/server/__init__.py
umodbus/server/tcp.py
umodbus/server/serial/__init__.py
umodbus/server/serial/rtu.py
