Metadata-Version: 2.1
Name: uModbus-extended
Version: 1.0.4
Summary: Implementation of the Modbus protocol in pure Python.
Home-page: https://github.com/Simonefardella/uModbus
Author: Simone Fardella
Author-email: fardella.simone@gmail.com
License: MPL
Platform: UNKNOWN
Classifier: Development Status :: 6 - Mature
Classifier: Intended Audience :: Developers
Classifier: License :: OSI Approved :: Mozilla Public License 2.0 (MPL 2.0)
Classifier: Operating System :: OS Independent
Classifier: Programming Language :: Python :: 2.7
Classifier: Programming Language :: Python :: 3.3
Classifier: Programming Language :: Python :: 3.4
Classifier: Programming Language :: Python :: 3.5
Classifier: Programming Language :: Python :: 3.6
Classifier: Topic :: Software Development :: Embedded Systems
Requires-Dist: pyserial (~=3.4)
